[
  {
    "id": 1,
    "createdDate": "24/12/2022",
    "shippedDate": "26/12/2022",
    "status": "sending",
    "description": "Dang qua trinh van chuyen",
    "shippingAddress": "HUE",
    "paymentType": "ship code"
  },
  {
    "id": 4,
    "createdDate": "24/12/2022",
    "shippedDate": "26/12/2022",
    "status": "sending",
    "description": "Dang qua trinh van chuyen",
    "shippingAddress": "HUE",
    "paymentType": "ship code"
  },
  {
    "id": 5,
    "createdDate": "24/12/2022",
    "shippedDate": "26/12/2022",
    "status": "sending",
    "description": "Dang qua trinh van chuyen",
    "shippingAddress": "HUE",
    "paymentType": "ship code"
  },
  {
    "id": 8,
    "createdDate": "24/12/2022",
    "shippedDate": "26/12/2022",
    "status": "sending",
    "description": "Dang qua trinh van chuyen",
    "shippingAddress": "HUE",
    "paymentType": "ship code"
  }
]
